Backtracking/AllPermutationsOfString.py
Backtracking/KthPermutationSequence.py
Backtracking/MColouringProblem.py
Backtracking/NQueens.py
Backtracking/SudokuSolving.py
Backtracking/__init__.py
Dynamic_Programming/CoinChange.py
Dynamic_Programming/EggDropping.py
Dynamic_Programming/KadanesAlgorithm.py
Dynamic_Programming/LongestCommonSequence.py
Dynamic_Programming/LongestCommonSubsequence.py
Dynamic_Programming/LongestIncreasingSubsequence.py
Dynamic_Programming/MaxProductSubarray.py
Dynamic_Programming/PalindromePartitioning.py
Dynamic_Programming/SubsetSum.py
Dynamic_Programming/WordBreak.py
Dynamic_Programming/ZeroOneKnapsack.py
Dynamic_Programming/__init__.py
Graph/Kruskals.py
Graph/Prims.py
Graph/__init__.py
Greedy/FractionalKnapsack.py
Greedy/__init__.py
Stack/CheckForBalancedParentheses.py
Stack/LargestRectangleInHistogram.py
Stack/NextGreaterElement.py
Stack/__init__.py
String/KMPAlgorithm.py
String/LongestCommonPrefix.py
String/NextPermutation.py
String/PrefixFunction.py
String/RabinKarp.py
String/ReverseWordsInGivenString.py
String/__init__.py
Tree/BinaryTreeFromInorderAndPostorder.py
Tree/BinaryTreeFromInorderAndPreorder.py
Tree/BottomViewOfBinaryTree.py
Tree/HeightOfBinaryTree.py
Tree/InorderTraversalOfBinaryTree.py
Tree/LCAOfBinaryTree.py
Tree/LeftViewOfBinaryTree.py
Tree/MaximumPathSumInBinaryTree.py
Tree/PostorderTraversalOfBinaryTree.py
Tree/PreorderTraversalOfBinaryTree.py
Tree/RightViewOfBinaryTree.py
Tree/TopViewOfBinaryTree.py
Tree/__init__.py
basic_algo-0.1.3.dist-info/LICENSE
basic_algo-0.1.3.dist-info/METADATA
basic_algo-0.1.3.dist-info/WHEEL
basic_algo-0.1.3.dist-info/top_level.txt
basic_algo-0.1.3.dist-info/RECORD
