Metadata-Version: 2.1
Name: basic-algo
Version: 0.1.3
Summary: Using basic algorithms
Home-page: https://github.com/kandarpkakkad/BasicAlgo
Author: Harsh Chaplot, Kandarp Kakkad
Author-email: 17bit026@nirmauni.ac.in, 17bit034@nirmauni.ac.in
License: UNKNOWN
Platform: UNKNOWN
Classifier: Programming Language :: Python :: 3
Classifier: License :: OSI Approved :: MIT License
Classifier: Operating System :: OS Independent
Requires-Python: >=3.6
